odoo/addons/mgmtsystem_action_template/README.rst
odoo/addons/mgmtsystem_action_template/__init__.py
odoo/addons/mgmtsystem_action_template/__manifest__.py
odoo/addons/mgmtsystem_action_template/i18n/it.po
odoo/addons/mgmtsystem_action_template/i18n/mgmtsystem_action_template.pot
odoo/addons/mgmtsystem_action_template/models/__init__.py
odoo/addons/mgmtsystem_action_template/models/mgmtsystem_action.py
odoo/addons/mgmtsystem_action_template/models/mgmtsystem_action_template.py
odoo/addons/mgmtsystem_action_template/readme/CONFIGURE.rst
odoo/addons/mgmtsystem_action_template/readme/CONTRIBUTORS.rst
odoo/addons/mgmtsystem_action_template/readme/DESCRIPTION.rst
odoo/addons/mgmtsystem_action_template/readme/HISTORY.rst
odoo/addons/mgmtsystem_action_template/readme/INSTALL.rst
odoo/addons/mgmtsystem_action_template/readme/ROADMAP.rst
odoo/addons/mgmtsystem_action_template/readme/USAGE.rst
odoo/addons/mgmtsystem_action_template/security/ir.model.access.csv
odoo/addons/mgmtsystem_action_template/static/description/icon.png
odoo/addons/mgmtsystem_action_template/static/description/index.html
odoo/addons/mgmtsystem_action_template/static/description/template.png
odoo/addons/mgmtsystem_action_template/tests/__init__.py
odoo/addons/mgmtsystem_action_template/tests/test_action_template.py
odoo/addons/mgmtsystem_action_template/views/mgmtsystem_action_template.xml
odoo/addons/mgmtsystem_action_template/views/mgmtsystem_action_views.xml
odoo11_addon_mgmtsystem_action_template-11.0.1.0.0.99.dev4.dist-info/METADATA
odoo11_addon_mgmtsystem_action_template-11.0.1.0.0.99.dev4.dist-info/WHEEL
odoo11_addon_mgmtsystem_action_template-11.0.1.0.0.99.dev4.dist-info/top_level.txt
odoo11_addon_mgmtsystem_action_template-11.0.1.0.0.99.dev4.dist-info/RECORD
